spaceshooter/__init__.py
spaceshooter/__main__.py
spaceshooter/arena.py
spaceshooter/game.py
spaceshooter/managers.py
spaceshooter/primi.py
spaceshooter/sconfig.py
spaceshooter/sdefs.py
spaceshooter/sevents.py
spaceshooter/slocales.py
spaceshooter/stypes.py
spaceshooter/sutils.py
spaceshooter/images/aicon.png
spaceshooter/images/aplayer0.png
spaceshooter/images/aplayer1.png
spaceshooter/images/aplayer2.png
spaceshooter/images/apteczka.png
spaceshooter/images/asterowiec.png
spaceshooter/images/bomba.png
spaceshooter/images/cup.png
spaceshooter/images/dom1.png
spaceshooter/images/dom2.png
spaceshooter/images/dom3.png
spaceshooter/images/drop.png
spaceshooter/images/dzialo.png
spaceshooter/images/enemy4.png
spaceshooter/images/enemy5.png
spaceshooter/images/enemy6.png
spaceshooter/images/enemy7.png
spaceshooter/images/enemy8.png
spaceshooter/images/enemy9.png
spaceshooter/images/explosion-1.png
spaceshooter/images/explosion-2.png
spaceshooter/images/explosion-3.png
spaceshooter/images/fabryka1.png
spaceshooter/images/fabryka2.png
spaceshooter/images/fabryka3.png
spaceshooter/images/flag_en.png
spaceshooter/images/flag_pl.png
spaceshooter/images/frozen_box.png
spaceshooter/images/indicator_black.png
spaceshooter/images/indicator_green.png
spaceshooter/images/indicator_red.png
spaceshooter/images/indicator_yellow.png
spaceshooter/images/light_ball.png
spaceshooter/images/missile-1.png
spaceshooter/images/missile-2.png
spaceshooter/images/missile-3.png
spaceshooter/images/missile-4.png
spaceshooter/images/missile-5.png
spaceshooter/images/missile-6.png
spaceshooter/images/next.png
spaceshooter/images/player0.png
spaceshooter/images/player2.png
spaceshooter/images/player3.png
spaceshooter/images/player_indicator.png
spaceshooter/images/prev.png
spaceshooter/images/pzm.png
spaceshooter/images/shield-green.png
spaceshooter/images/smoke-1.png
spaceshooter/images/smoke-2.png
spaceshooter/images/smoke-3.png
spaceshooter/images/smoke-4.png
spaceshooter/images/star.png
spaceshooter-0.0.10.dist-info/LICENSE
spaceshooter-0.0.10.dist-info/METADATA
spaceshooter-0.0.10.dist-info/WHEEL
spaceshooter-0.0.10.dist-info/top_level.txt
spaceshooter-0.0.10.dist-info/RECORD
