Metadata-Version: 2.1
Name: spaceshooter
Version: 0.0.10
Summary: Simple spaceshooter game that uses PySide library
Home-page: https://iostream.pl/spaceshooter-en
Author: Marcin Bielewicz
Author-email: marcin.bielewicz@gmail.com
License: GPL
Project-URL: Bug Tracker, https://github.com/lvajxi03/spaceshooter/issues
Keywords: pyqt spaceshooter game arcade
Classifier: Development Status :: 4 - Beta
Classifier: Topic :: Games/Entertainment :: Side-Scrolling/Arcade Games
Classifier: License :: OSI Approved :: GNU General Public License (GPL)
Requires-Python: >=3.8
License-File: LICENSE
Requires-Dist: PySide6
